alexandrainst_ragger/__init__.py
alexandrainst_ragger/cli.py
alexandrainst_ragger/constants.py
alexandrainst_ragger/data_models.py
alexandrainst_ragger/demo.py
alexandrainst_ragger/document_store.py
alexandrainst_ragger/embedder.py
alexandrainst_ragger/embedding_store.py
alexandrainst_ragger/exceptions.py
alexandrainst_ragger/generator.py
alexandrainst_ragger/rag_system.py
alexandrainst_ragger/retriever.py
alexandrainst_ragger/utils.py
alexandrainst_ragger/webui_utils.py
alexandrainst_ragger-5.1.1.dist-info/METADATA
alexandrainst_ragger-5.1.1.dist-info/WHEEL
alexandrainst_ragger-5.1.1.dist-info/entry_points.txt
alexandrainst_ragger-5.1.1.dist-info/RECORD
