Metadata-Version: 2.4
Name: alexandrainst_ragger
Version: 5.1.1
Summary: A repository for general-purpose RAG applications.
Author-email: Dan Saattrup Nielsen <dan.nielsen@alexandra.dk>, Anders Jess Pedersen <anders.j.pedersen@alexandra.dk>
Maintainer-email: Dan Saattrup Nielsen <dan.nielsen@alexandra.dk>
License: Proprietary
Requires-Python: <4.0,>=3.10
Requires-Dist: click>=8.1.7
Requires-Dist: numpy>=1.25.0
Requires-Dist: openai>=1.50.0
Requires-Dist: pydantic>=2.9.2
Requires-Dist: python-dotenv>=1.0.1
Requires-Dist: pyyaml>=6.0.2
Requires-Dist: tiktoken>=0.8.0
Provides-Extra: demo
Requires-Dist: gradio>=5.4.0; extra == 'demo'
Provides-Extra: keyword-search
Requires-Dist: rank-bm25>=0.2.2; extra == 'keyword-search'
Provides-Extra: onprem-cpu
Requires-Dist: llama-cpp-python>=0.3.1; extra == 'onprem-cpu'
Requires-Dist: outlines>=0.0.46; extra == 'onprem-cpu'
Requires-Dist: protobuf>=5.28.3; extra == 'onprem-cpu'
Requires-Dist: sentence-transformers>=3.2.1; extra == 'onprem-cpu'
Requires-Dist: transformers>=4.46.1; extra == 'onprem-cpu'
Provides-Extra: onprem-gpu
Requires-Dist: outlines>=0.1.1; extra == 'onprem-gpu'
Requires-Dist: protobuf>=5.28.3; extra == 'onprem-gpu'
Requires-Dist: sentence-transformers>=3.2.1; extra == 'onprem-gpu'
Requires-Dist: transformers>=4.46.1; extra == 'onprem-gpu'
Requires-Dist: vllm>=0.1.0; extra == 'onprem-gpu'
Provides-Extra: postgres
Requires-Dist: psycopg2-binary>=2.9.10; extra == 'postgres'
